dcc_mcp_core/__init__.py
dcc_mcp_core/actions/__init__.py
dcc_mcp_core/actions/adapter.py
dcc_mcp_core/actions/base.py
dcc_mcp_core/actions/events.py
dcc_mcp_core/actions/generator.py
dcc_mcp_core/actions/manager.py
dcc_mcp_core/actions/middleware.py
dcc_mcp_core/actions/registry.py
dcc_mcp_core/constants.py
dcc_mcp_core/log_config.py
dcc_mcp_core/models.py
dcc_mcp_core/template/action.template
dcc_mcp_core/utils/__init__.py
dcc_mcp_core/utils/decorators.py
dcc_mcp_core/utils/dependency_injector.py
dcc_mcp_core/utils/exceptions.py
dcc_mcp_core/utils/filesystem.py
dcc_mcp_core/utils/module_loader.py
dcc_mcp_core/utils/pydantic_extensions.py
dcc_mcp_core/utils/result_factory.py
dcc_mcp_core/utils/template.py
dcc_mcp_core/utils/type_wrappers.py
dcc_mcp_core-0.8.0.dist-info/LICENSE
dcc_mcp_core-0.8.0.dist-info/METADATA
dcc_mcp_core-0.8.0.dist-info/WHEEL
dcc_mcp_core-0.8.0.dist-info/RECORD
