Metadata-Version: 2.3
Name: dcc-mcp-core
Version: 0.8.0
Summary: Foundational library for the DCC Model Context Protocol (MCP) ecosystem
License: MIT
Author: longhao
Author-email: hal.long@outlook.com
Requires-Python: >=3.7,<4.0
Classifier: Development Status :: 3 - Alpha
Classifier: Intended Audience :: Developers
Classifier: License :: OSI Approved :: MIT License
Classifier: Programming Language :: Python :: 3
Classifier: Programming Language :: Python :: 3.7
Classifier: Programming Language :: Python :: 3.8
Classifier: Programming Language :: Python :: 3.9
Classifier: Programming Language :: Python :: 3.10
Classifier: Programming Language :: Python :: 3.11
Classifier: Programming Language :: Python :: 3.12
Classifier: Programming Language :: Python :: 3.13
Classifier: Topic :: Multimedia :: Graphics :: 3D Modeling
Classifier: Topic :: Software Development :: Libraries
Requires-Dist: importlib_metadata (>=4.6.0) ; python_version < "3.8"
Requires-Dist: jinja2 (>=3.0.0)
Requires-Dist: loguru (>=0.7.3,<0.8.0)
Requires-Dist: platformdirs (>=3,<4.0.0)
Requires-Dist: pydantic (>=2.0.0,<3.0.0)
Project-URL: Homepage, https://github.com/loonghao/dcc-mcp-core
Project-URL: Issues, https://github.com/loonghao/dcc-mcp-core/issues
Project-URL: Repository, https://github.com/loonghao/dcc-mcp-core
